[{"tweetDate":"Tue Mar 21 17:47:55 +0000 2023","content":"ุทูู ุนูุฑู ูุง ุญ ุงูุณู ููุงู ุจูููุณ ูู ุนุฑุถ ุจูุช ููุชู ููุธูููุฉ ูุงุณุชุดุฑุงููุง ุนูู ุจูุช ุงุดุฑู ูู ุงูุดุฑู ููู ุจุชุญุถู ูู ุงูุฑุฌุงู ุงู(ุบุฑุจุงุก) ููุงุดูุฉ #ุงุณุฑุงุก_ุบุฑูุจ #ุจูููุณ https://t.co/Ao005pPCuA","twitterProfile":"https://twitter.com/Ta_kralicesi","tweetUrl":"https://twitter.com/Ta_kralicesi/status/1638236007400087572","timestamp":"2025-04-09T17:54:01.007Z","query":"#ุงุณุฑุงุก_ุบุฑูุจ"},{"tweetDate":"Thu Jan 05 12:58:46 +0000 2023","content":"ูู ุจุฏุงูุฉ ูุถูุฉ ุงููุฑุญููุฉ #ุงุณุฑุงุก_ุบุฑูุจ ุชู ุงุทูุงู ูุงุดุชุงุบ #ูููุง_ุงุณุฑุงุก_ุบุฑูุจ ุจุนุฏูุง ุงูุนุงูู ููู ุณูุน ุตูุช ุตุฑุงุฎูุง ุจุงููุดูู ููู ุชุถุฑุจ ุจุฏุงุฎูู ููุฐุง ูู ุงูุชุณุฌูู ุงูุฐู ููุถุญ ุงูู ููุฌุฏ ุงุนุชุฏุงุก ุนูู ุงุณุฑุงุก ูู ุงูุบุฑูุฉ..ุนููุง ุงูู ุชู ุถุฑุจูุง ุงูุถุง ูุจู ุงููุดูู ูุงูุฏููู ุงููุฏูุงุช ุงูุชู ูุงูุช ุนูู ูุฏูุง https://t.co/e1LDtAPzY7","twitterProfile":"https://twitter.com/Khaled1haddad","tweetUrl":"https://twitter.com/Khaled1haddad/status/1610984149711470594","timestamp":"2025-04-09T17:54:01.007Z","query":"#ุงุณุฑุงุก_ุบุฑูุจ"},{"tweetDate":"Mon Jan 09 17:55:27 +0000 2023","content":"ุงููู ูุฑุญู #ุงุณุฑุงุก_ุบุฑูุจ \n\n๐๐ป https://t.co/YA9uy5Lbhm","twitterProfile":"https://twitter.com/al_m6eriah","tweetUrl":"https://twitter.com/al_m6eriah/status/1612508363354406912","timestamp":"2025-04-09T17:54:01.007Z","query":"#ุงุณุฑุงุก_ุบุฑูุจ"},{"tweetDate":"Tue Sep 03 21:50:09 +0000 2019","content":"ุจุนุฏ ุงูุถุบุท ุงููุจูุฑ ูู ุฑูุงุฏ ููุงูุน ุงูุชูุงุตู ูุชุญููู ุบููุถ ููุงุชูุง ุงูู ูุถูุฉ ุฑุฃู ุนุงู ุนุฑุจู  /   ุงูุจุนุถ ูุญุชุฌุฒ ุฑูู ุงูุชุญููู .. \n#ุงุณุฑุงุก_ุบุฑูุจ \n\nููุฃู ุฃุญุฏูู ูุฏุฏ ุจููุงุถุงุชู ุจุนุฏ ุฃู ุบุฑุฏุช ุนู ูุฐู ุงููุถูุฉ ุ ๐ https://t.co/IJOQCbJyM2","twitterProfile":"https://twitter.com/OlaAlfares","tweetUrl":"https://twitter.com/OlaAlfares/status/1169004681928089600","timestamp":"2025-04-09T17:54:01.007Z","query":"#ุงุณุฑุงุก_ุบุฑูุจ"},{"tweetDate":"Tue Jun 25 01:03:40 +0000 2024","content":"ุงูุฏููุง ุฏูุงุฑุฉ ูุงูููุงู ุงููู ููุชูู ุนูู #ุงุณุฑุงุก_ุบุฑูุจ ูุงุนุฏ ูุฏูุฑ ุนููู #ุชุจููู_ุจูููุณ https://t.co/3kG1uLlEvI","twitterProfile":"https://twitter.com/koka_koka1929","tweetUrl":"https://twitter.com/koka_koka1929/status/1805406473872167032","timestamp":"2025-04-09T17:54:01.007Z","query":"#ุงุณุฑุงุก_ุบุฑูุจ"},{"tweetDate":"Thu Jan 05 14:58:43 +0000 2023","content":"#ุงุณุฑุงุก_ุบุฑูุจ \n ุงูุชูู ูู ููุงู ููุณ ุจูู ูููู ูุง ุทุจุนุง ูููุฌุฏ ุงูุชุณุฌูู ุงูุตูุชู ุงูุฐู ุจุฏุฃ ุจูููุฉ ุงุชุฑูููู ูู ุงููุดูู ูุงูุชูู ุจุฌููุฉ ุจุฏู ุงุฎุงู ูู ุงูุดุฑุทุฉ ุงูุง ูู ูุจู ูุณุฑูู ูุงูุชู ูุฑุฌุญ ุงููุง ูุณุฑูู ุฌููู!!!!\n.ุชุฒุงููุง ูุน ุฐูู ูุดุฑ ุงุญุฏ ุงูุงุดุฎุงุต ูู ุงูุงุฑุฏู ุงูู ุงูุฌุฑููุฉ ููุง ุนูุงูุฉ ุจุงูุดุจูุงุช!!! ููู ุชููู ุฏูู ุฏูุงุฆู https://t.co/ftYVbIVYhV","twitterProfile":"https://twitter.com/Khaled1haddad","tweetUrl":"https://twitter.com/Khaled1haddad/status/1611014337681825795","timestamp":"2025-04-09T17:54:01.007Z","query":"#ุงุณุฑุงุก_ุบุฑูุจ"},{"tweetDate":"Wed Jun 26 06:33:46 +0000 2024","content":"ุงุนุชูุฏุช ุงู ุญููุฉ #ุชุจููู_ุจูููุณ ุญูุจุฉ #ุงุณุฑุงุก_ุบุฑูุจ\nุงุซุงุฑู ูุณุจุจ ูุงูููุทุน \nูู ุชูุตุฏ ุจูููุณ ุจุงููู ูุชุขูุฑูู ุนูููุง ูู ุชุญุช ุงูุทุงููุฉุ\nูู ูู ุงููู ุนุงูููู ุฒู ุจุงุจูู ุงุณููุจุงุฑุ\nูู ุงููู ููู ูุฏูุฑูุง ุ\nููุฑู ูุชุนุฑููู ูู ุชูุตุฏ ูุงููุง ุฌุฏ ุงุณุงุกุช ูุจููุฉ ุงููู ูุดูููุง ููููุฉ ูุฑูุญ https://t.co/BbCkW6Wjup","twitterProfile":"https://twitter.com/haasmood","tweetUrl":"https://twitter.com/haasmood/status/1805851930855387244","timestamp":"2025-04-09T17:54:01.007Z","query":"#ุงุณุฑุงุก_ุบุฑูุจ"},{"tweetDate":"Mon Jul 10 17:29:45 +0000 2023","content":"ุฅูู ุฑูุญ #ุฅุณุฑุงุก_ุบุฑูุจ\n\nููู ูุงุณ ุจุชูุนุจ ููุฑุฉ ..\nูู ุงูุดุงุฑุน\nููุงุณ ุจุชูุดู ุชุบููุ ุชุงุฎุฏ ุตูุฑุฉ ..\nูู ุงูุดุงุฑุน\nููู ูุงุณ ุจุชุดุชู ุจุนุถุ\nุชุถุฑุจ ุจุนุถุ\nุชูุชู ุจุนุถ ..\nูู ุงูุดุงุฑุน\nููู ูุงุณ ุชูุงู ุนูู ุงูุฃุฑุถ ..\nูู ุงูุดุงุฑุน\nููุงุณ ุชุจูุน ุงูุนุฑุถ ..\nูู ุงูุดุงุฑุน\nููู ุงูุดุงุฑุน ..\nุฃุฎุทุงุก ูุชูุฑ ุตุจุญุช ุตุญูุญุฉ https://t.co/LtA98KuypR","twitterProfile":"https://twitter.com/BooksPhilo79515","tweetUrl":"https://twitter.com/BooksPhilo79515/status/1678456489109856268","timestamp":"2025-04-09T17:54:01.007Z","query":"#ุงุณุฑุงุก_ุบุฑูุจ"},{"tweetDate":"Mon Feb 19 20:32:56 +0000 2024","content":"ุงู ุฑ ู ุฉ ุงููุณุชุดุฑูุฉ ุงููู ุงุณุชุบูุช ูุถูุฉ #ุงุณุฑุงุก_ุบุฑูุจ ูุทุงูุจุช ุงูุฑุฌู ูุนูู ุงูุจูุช ุจุงูุณุฑ ุนุดุงู ุงููุถูุญุฉ #ุจูููุณ_ูุชุญู ุงููุทููุฉ ุงูุนุง ู ุฑ ุฉ ุงููู ูุงููุช ุฑุฌู ูุถุจูุง","twitterProfile":"https://twitter.com/batwoman780","tweetUrl":"https://twitter.com/batwoman780/status/1759677467961286822","timestamp":"2025-04-09T17:54:01.007Z","query":"#ุงุณุฑุงุก_ุบุฑูุจ"},{"tweetDate":"Thu Jan 05 16:45:15 +0000 2023","content":"ุงููู ูุฑุญูู #ุงุณุฑุงุก_ุบุฑูุจ \n#ูููุง_ุงุณุฑุงุก_ุบุฑูุจ\n#ุงูุนุฏุงูุฉ_ูุฅุณุฑุงุก_ุบุฑูุจ \n#ุชุณุฌูู_ุฎุฑูุฌ \nุฎูุต ุงูุญูู https://t.co/0whrhtgsFi","twitterProfile":"https://twitter.com/Khaled1haddad","tweetUrl":"https://twitter.com/Khaled1haddad/status/1611041144443478016","timestamp":"2025-04-09T17:54:01.007Z","query":"#ุงุณุฑุงุก_ุบุฑูุจ"},{"tweetDate":"Wed Oct 11 07:26:36 +0000 2023","content":"ูุง ูุณููุง #ุงุณุฑุงุก_ุบุฑูุจ ูุง ุดุฑูุงุก . https://t.co/0R9YNPUk7W","twitterProfile":"https://twitter.com/BrAiN1StOrMiNg","tweetUrl":"https://twitter.com/BrAiN1StOrMiNg/status/1712006770598535381","timestamp":"2025-04-09T17:54:01.007Z","query":"#ุงุณุฑุงุก_ุบุฑูุจ"},{"tweetDate":"Thu Sep 12 08:12:08 +0000 2019","content":"ูุฃูู ูู ุงููุถุงุก ููู ููุธุฑ ูู ุงููุถูุฉ ุงู ูุง ูุญุตุฑูุง ูู ุงูุถุฑุจ ุงููููุถู ููููุช ููุฏ ูุงู ูุงุถุญุง ุชูุงูุฑ ููุฉ ุงููุชู ูุง ุงูุชูุงุกูุง \"ุงููุตุฏ ุงูุฌูุงุฆู\" ูู ุฎูุงู ุชููุฑ ุธุฑู ุณุจู ุงูุฅุตุฑุงุฑ ุจุชูุฑุงุฑ ุงูุถุฑุจ ูุงูุฅููุงู ูุงูุฎ ูู ุญูุซูุงุช ุงููุถูุฉ ุ ูุทุงูุจ ุจุฃูุณู ูุฃูุตู  ุฏุฑุฌุงุช ุงูุนููุจุฉ ุงุญูุงูุง ููุญู ู ุฅูุงูุฉู ุงูุนุฏุงูุฉ #ุงุณุฑุงุก_ุบุฑูุจ","twitterProfile":"https://twitter.com/OlaAlfares","tweetUrl":"https://twitter.com/OlaAlfares/status/1172060310758465537","timestamp":"2025-04-09T17:54:01.007Z","query":"#ุงุณุฑุงุก_ุบุฑูุจ"},{"tweetDate":"Thu Jun 06 05:09:57 +0000 2024","content":"ุนูุฏูุง ุงูุนูุงุฆู ูู ูุซุฑ ูุงูู ูุชุฑุงุจุทู ูุญุฑุดูู ุนูู ุจุนุถ๐๐ผโค๏ธ\nููุง ุจูุตุฉ #ุงุณุฑุงุก_ุบุฑูุจ ุฎูุฑ ูุซุงู","twitterProfile":"https://twitter.com/24hWhat","tweetUrl":"https://twitter.com/24hWhat/status/1798583083324850410","timestamp":"2025-04-09T17:54:01.007Z","query":"#ุงุณุฑุงุก_ุบุฑูุจ"},{"tweetDate":"Tue Sep 03 15:49:35 +0000 2019","content":"#ุญููุฉ_ุงูุบุงุก_ุงููุงุฏุฉ_ูกูฅูฃ \nุงูุชุดุฑ ูุฐุง ุงูุญุณุงุจ ูู ุชููุชุฑ ุจุฃุณู ุถุญูุฉ ุงููุชู ุงูุชู ูุฌุฏุช ูู ุจุฑ ุงูุณุงููู ูู ุฏููุฉ ุงููููุช ุจุนุฏ ุญุงุฏุซุฉ ูุชู #ุงุณุฑุงุก_ุบุฑูุจ. ูุง ุญูู ููุง ููุฉ ุงูุง ุจุงููู. https://t.co/qFX9unDrOn","twitterProfile":"https://twitter.com/abolish153","tweetUrl":"https://twitter.com/abolish153/status/1168913939473866763","timestamp":"2025-04-09T17:54:01.007Z","query":"#ุงุณุฑุงุก_ุบุฑูุจ"},{"tweetDate":"Wed Mar 01 23:00:52 +0000 2023","content":"#ููุฑุฉ_ุฃุดุฑู \n#ุทูุจุฉ_ุงูุนูู \n#ุงุณุฑุงุก_ุบุฑูุจ\nโฆ https://t.co/1jNw6l7bLn","twitterProfile":"https://twitter.com/jaw_haraa","tweetUrl":"https://twitter.com/jaw_haraa/status/1631067005888462848","timestamp":"2025-04-09T17:54:01.007Z","query":"#ุงุณุฑุงุก_ุบุฑูุจ"},{"tweetDate":"Fri Aug 30 02:38:02 +0000 2019","content":"ูู ุฃุณุชุทุน ุงูููู ูุฐู ุงููููุฉ..ุตูุช ุตุฑุงุฎูุง ูู ุงููุณุชุดูู ูู ุงูููุฏูู ุงููุชุฏุงูู ูุง ูููุงุฑููู.\n#ุงุณุฑุงุก_ุบุฑูุจ ุงููู ูุฑุญููุง \nุชุคูุฏ ุจุนุถ ุงูุฌูุงุช\nุงููุง ุชุนุฑุถุช ููุถุฑุจ ุงูููุถู ููููุช \nุฃุฑูุถ ุงูุธูู  ูุงูุฅุถุทูุงุฏ ุจูู ุงุดูุงูู ููู ุนูุฏูุง  ูููุงุฑุณ ุนูู ุฅูุฑุฃุฉ!\n  \"ุงููู ููุชูู ูู  ูู ุณุงูุท ููุงุฑุณ ุชุฎููู ูุฌููู ูุชุณูุทู ุนูู ุงูุฑุฃุฉ\" https://t.co/iNKSpVLlnb","twitterProfile":"https://twitter.com/OlaAlfares","tweetUrl":"https://twitter.com/OlaAlfares/status/1167265187705032707","timestamp":"2025-04-09T17:54:01.007Z","query":"#ุงุณุฑุงุก_ุบุฑูุจ"},{"tweetDate":"Wed Jun 26 00:12:16 +0000 2024","content":"ุฒุญู ุจุฏุง ุจุชุฑุงุฌุน ูุฑุฌุนู ูุฌูุฏูู ุจูุงูุงูุณุงูู ูุนูุงู ุงูุญู ูุง ูุถูุน #ุงุณุฑุงุก_ุบุฑูุจ https://t.co/cd0BZEeISi","twitterProfile":"https://twitter.com/on101o","tweetUrl":"https://twitter.com/on101o/status/1805755924168294828","timestamp":"2025-04-09T17:54:01.007Z","query":"#ุงุณุฑุงุก_ุบุฑูุจ"},{"tweetDate":"Mon Jun 24 02:59:12 +0000 2024","content":"@peoplebelarabi @BalqeesFathi ุงุญูุง ูุดุนุจ ุณุนูุฏู ูุงูุจุบุงู ููุงูุณููุง ุจุดุงุนุชู ู ูุถูุฉ #ุฅุณุฑุงุก_ุบุฑูุจ ุงุฑุงููู ูุงุตุงุฑุช ุงุบุงููู ุชุฑูุฏ ูุงูุณุนูุฏูู ุงูุง ูู ุงูุงุฌุงูุจ ูุงูุง ุงูุณุนูุฏุฏูู ูููู ูุญุฏ ูุฏุงููู ูุตูุชู ูุดุงุฒ ูุฑูุชุงูุง ุณุญุจุช ุนููู ูุนูู ูุฑุชู ูุญุฑูู ููุณ ูุฑุช ููุง ุงูุดุนูุจู","twitterProfile":"https://twitter.com/roni_1s","tweetUrl":"https://twitter.com/roni_1s/status/1805073159810695315","timestamp":"2025-04-09T17:54:01.007Z","query":"#ุงุณุฑุงุก_ุบุฑูุจ"},{"tweetDate":"Fri Apr 05 17:57:29 +0000 2024","content":"ุงูู ูุง ุงุณูุน ูุถูุฉ ุดุฑู ุงุชุฐูุฑ ูุตุฉ #ุงุณุฑุงุก_ุบุฑูุจ ูููู ุงููุชูุช ุธูู ููู ุณุจุจ ุจุณูุท ุจุณ ูุงููุงุชู ูุนุซ ุจุงูุงุฑุถ ุงููุณุงุฏ ุงูู ุงูุงู","twitterProfile":"https://twitter.com/im01_","tweetUrl":"https://twitter.com/im01_/status/1776308192592478479","timestamp":"2025-04-09T17:54:01.007Z","query":"#ุงุณุฑุงุก_ุบุฑูุจ"},{"tweetDate":"Wed Jan 10 21:42:00 +0000 2024","content":"ุณุงุจูุงู ูุฌูุช ุชุบุฑูุฏุงุช ูููุจ ุงูุฅุณุฑุงุฆููููู ุงููุฎูุซ #ูุญููุฏ_ุนุจุงุณ ููู ููู ุฎููู ูู ูุฎูุซูู ุดุจูุงุช ุงูุฏุนุงุฑุฉ ูู \"ููุณุทูู ูกูฉูกูฉ\"\nุจุฎุตูุต ููุถูุน ุฌุฑููุฉ \"ูุชู\" #ุฅุณุฑุงุก_ุบุฑูุจ\n\nูุฐู ุงูุชุบุฑูุฏุฉ ุนุดุงู ูุงูููุจ ูุง ูููุฑ ุงูู ุงูุชุณู ุงูููุถูุน ูุน ุงูููุช.\n\nูุนุดุงู ุงูููุงุจ ุงูุจุงููุฉ ุชุนุฑู ..\nุฃู ูุง ูุญุฏุซ ูู ุบุฒุฉ ูู ููุณุงู.","twitterProfile":"https://twitter.com/abdmad527","tweetUrl":"https://twitter.com/abdmad527/status/1745199334080028867","timestamp":"2025-04-09T17:54:01.007Z","query":"#ุงุณุฑุงุก_ุบุฑูุจ"},{"error":"No tweets found","timestamp":"2025-04-09T17:54:06.112Z","query":"#ูููุง_ุงุณุฑุงุก_ุงูุบุฑูุจ"},{"error":"No tweets found","timestamp":"2025-04-09T17:54:09.269Z","query":"#ุฅุณุฑุงุก_ุบุฑูุจ"},{"error":"No tweets found","timestamp":"2025-04-09T17:54:11.052Z","query":"#weareallisraa"},{"error":"No tweets found","timestamp":"2025-04-09T17:54:12.790Z","query":"#Israa_Ghrayeb"}]